{
  "project_info": {
    "project_number": "84493698601",
    "firebase_url": "https://homeautomation-f48d2.firebaseio.com",
    "project_id": "homeautomation-f48d2",
    "storage_bucket": "homeautomation-f48d2.appspot.com"
  },
  "client": [
    {
      "client_info": {
        "mobilesdk_app_id": "1:84493698601:android:6974f9d6bb89c13ebf3e38",
        "android_client_info": {
          "package_name": "com.baserythm.homeautomationubaid"
        }
      },
      "oauth_client": [
        {
          "client_id": "84493698601-udse8a58pomsudlo25uvva5jfaeshf7v.apps.googleusercontent.com",
          "client_type": 3
        }
      ],
      "api_key": [
        {
          "current_key": "AIzaSyCxyQq05-Ujj55fBeMOjTFTFR_3gjc3jxs"
        }
      ],
      "services": {
        "appinvite_service": {
          "other_platform_oauth_client": [
            {
              "client_id": "84493698601-udse8a58pomsudlo25uvva5jfaeshf7v.apps.googleusercontent.com",
              "client_type": 3
            }
          ]
        }
      }
    },
    {
      "client_info": {
        "mobilesdk_app_id": "1:84493698601:android:ca959450b3beab90bf3e38",
        "android_client_info": {
          "package_name": "com.example.homeautomation"
        }
      },
      "oauth_client": [
        {
          "client_id": "84493698601-5cp8qvj20ekjrciif6f5sqknii5qd8p4.apps.googleusercontent.com",
          "client_type": 1,
          "android_info": {
            "package_name": "com.example.homeautomation",
            "certificate_hash": "d23a081a928e6db48037c39f8911418c2a98e038"
          }
        },
        {
          "client_id": "84493698601-udse8a58pomsudlo25uvva5jfaeshf7v.apps.googleusercontent.com",
          "client_type": 3
        }
      ],
      "api_key": [
        {
          "current_key": "AIzaSyCxyQq05-Ujj55fBeMOjTFTFR_3gjc3jxs"
        }
      ],
      "services": {
        "appinvite_service": {
          "other_platform_oauth_client": [
            {
              "client_id": "84493698601-udse8a58pomsudlo25uvva5jfaeshf7v.apps.googleusercontent.com",
              "client_type": 3
            }
          ]
        }
      }
    }
  ],
  "configuration_version": "1"
}